README.md
setup.py
frasco_babel/__init__.py
frasco_babel/form.py
frasco_babel.egg-info/PKG-INFO
frasco_babel.egg-info/SOURCES.txt
frasco_babel.egg-info/dependency_links.txt
frasco_babel.egg-info/not-zip-safe
frasco_babel.egg-info/requires.txt
frasco_babel.egg-info/top_level.txt