Metadata-Version: 1.0
Name: frasco-babel
Version: 0.4.8
Summary: I18n and L10n support for Frasco
Home-page: http://github.com/frascoweb/frasco-babel
Author: Maxime Bouroumeau-Fuseau
Author-email: maxime.bouroumeau@gmail.com
License: MIT
Platform: any
